gui/__init__.py
GAM_chat_client-0.1.1.dist-info/METADATA
GAM_chat_client-0.1.1.dist-info/WHEEL
GAM_chat_client-0.1.1.dist-info/top_level.txt
GAM_chat_client-0.1.1.dist-info/RECORD
