Metadata-Version: 2.1
Name: GAM-chat-client
Version: 0.1.1
Summary: Тестовый проект
Author: Andrei G.
Author-email: andrei_gosovich@mail.ru
Requires-Dist: PyQt6
Requires-Dist: sqlalchemy
